mgedb/__init__.py
mgedb/cli.py
mgedb/db.py
mgedb/extract.py
mgedb/io.py
mgedb/sequence.py
mgedb/update.py
mgedb/validate.py
mgedb/version.py
mgedb/data/mge_nomenclature.json
mgedb/data/mge_records.json
mgedb/data/references.json
mgedb/data/sequences.d/mge_cds.faa
mgedb/data/sequences.d/mge_records.fna
MGEdb-1.1.1.dist-info/LICENSE
MGEdb-1.1.1.dist-info/METADATA
MGEdb-1.1.1.dist-info/WHEEL
MGEdb-1.1.1.dist-info/entry_points.txt
MGEdb-1.1.1.dist-info/top_level.txt
MGEdb-1.1.1.dist-info/RECORD
