Metadata-Version: 2.1
Name: MGEdb
Version: 1.1.1
Summary: Mobile Genetic Element database
Home-page: https://bitbucket.org/mhkj/mgedb/
Author: Markus Johansson
Author-email: markus.johansson@me.com
License: GPLv3
Platform: UNKNOWN
Classifier: License :: OSI Approved :: GNU General Public License v3 (GPLv3)
Classifier: Programming Language :: Python :: 3.6
Classifier: Programming Language :: Python :: 3.7
Classifier: Programming Language :: Python :: 3.8
Requires-Python: >=3.6
Requires-Dist: attrs
Requires-Dist: biopython
Requires-Dist: cattrs
Requires-Dist: Click
Requires-Dist: tabulate
